morph_api_tomcart/__init__.py
morph_api_tomcart/workflow.py
morph_api_tomcart-0.2.1.dist-info/METADATA
morph_api_tomcart-0.2.1.dist-info/WHEEL
morph_api_tomcart-0.2.1.dist-info/top_level.txt
morph_api_tomcart-0.2.1.dist-info/RECORD
