Metadata-Version: 2.1
Name: morph-api-tomcart
Version: 0.2.1
Summary: Morpheus API Functions
Home-page: https://github.com/BeepBoopRobit
Author: Ricky Nelson, Michael Escobar
Author-email: rnelson@thetomcart.com, miescobar@deloitte.com
License: UNKNOWN
Platform: UNKNOWN
Requires-Dist: requests
Requires-Dist: isodate
